ovsd_tools/__init__.py
ovsd_tools/main.py
ovsd_tools/options.py
ovsd_tools/utils/__init__.py
ovsd_tools/utils/tools.py
ovsd_tools-1.0.2.dist-info/METADATA
ovsd_tools-1.0.2.dist-info/WHEEL
ovsd_tools-1.0.2.dist-info/top_level.txt
ovsd_tools-1.0.2.dist-info/RECORD
