Metadata-Version: 2.1
Name: ovsd-tools
Version: 1.0.2
Summary: Packages for simple implementations of Stable Diffusion with OpenVINO
Home-page: https://github.com/suk-6/ovsd-tools
Author: suk-6
Author-email: me@suk.kr
License: MIT
Requires-Python: >=3.6
Requires-Dist: torch
Requires-Dist: openvino
Requires-Dist: diffusers
Requires-Dist: transformers
Requires-Dist: accelerate
Requires-Dist: scipy
Requires-Dist: huggingface-hub
Requires-Dist: opencv-python
